type_comparable/__init__.py
type_comparable/pytest_plugin.py
type_comparable-2.1.dist-info/LICENSE
type_comparable-2.1.dist-info/METADATA
type_comparable-2.1.dist-info/WHEEL
type_comparable-2.1.dist-info/entry_points.txt
type_comparable-2.1.dist-info/top_level.txt
type_comparable-2.1.dist-info/RECORD
