Metadata-Version: 2.2
Name: type_comparable
Version: 2.1
Summary: Helper for checking variable equivalence by type. Useful for tests.
Home-page: https://github.com/sirkonst/type_comparable
Author: Konstantin Enchant
Author-email: sirkonst@gmail.com
Maintainer: Konstantin Enchant
Maintainer-email: sirkonst@gmail.com
License: MIT
Keywords: test,tests,pytest,pytest-pluggin,type,typing
Classifier: Development Status :: 5 - Production/Stable
Classifier: License :: OSI Approved :: MIT License
Classifier: Programming Language :: Python :: 3 :: Only
Classifier: Programming Language :: Python :: 3.7
Classifier: Programming Language :: Python :: 3.8
Classifier: Programming Language :: Python :: 3.9
Classifier: Programming Language :: Python :: 3.10
Classifier: Programming Language :: Python :: 3.11
Classifier: Programming Language :: Python :: 3.12
Classifier: Programming Language :: Python :: 3.13
Classifier: Framework :: Pytest
Requires-Python: >=3.7
License-File: LICENSE
Requires-Dist: wrapt~=1.15
Provides-Extra: develop
Requires-Dist: coverage~=7.2; extra == "develop"
Requires-Dist: docutils~=0.20; extra == "develop"
Requires-Dist: pygments~=2.16; extra == "develop"
Requires-Dist: pylama~=8.4; extra == "develop"
Requires-Dist: pytest-xdist; extra == "develop"
Requires-Dist: pytest~=7.2; extra == "develop"
Requires-Dist: setuptools~=68.2; python_version >= "3.12" and extra == "develop"
Requires-Dist: tox~=4.8; extra == "develop"
Requires-Dist: twine~=4.0; extra == "develop"
Requires-Dist: wheel~=0.38; extra == "develop"
